shifthappens/__init__.py
shifthappens/benchmark.py
shifthappens/model_comparison.py
shifthappens/utils.py
shifthappens/data/__init__.py
shifthappens/data/base.py
shifthappens/data/imagenet.py
shifthappens/data/torch.py
shifthappens/models/__init__.py
shifthappens/models/base.py
shifthappens/models/mixins.py
shifthappens/models/torchvision.py
shifthappens/task_data/__init__.py
shifthappens/task_data/task_metadata.py
shifthappens/task_data/task_registration.py
shifthappens/tasks/__init__.py
shifthappens/tasks/base.py
shifthappens/tasks/metrics.py
shifthappens/tasks/mixins.py
shifthappens/tasks/task_result.py
shifthappens/tasks/utils.py
shifthappens-0.0.1a0.dist-info/LICENSE
shifthappens-0.0.1a0.dist-info/METADATA
shifthappens-0.0.1a0.dist-info/WHEEL
shifthappens-0.0.1a0.dist-info/top_level.txt
shifthappens-0.0.1a0.dist-info/RECORD
