Metadata-Version: 2.1
Name: shifthappens
Version: 0.0.1a0
Summary: Benchmark for image classifiers created for the Shift Happens ICML 2022 workshop
Home-page: https://shift-happens-benchmark.github.io
Author: Julian Bitterwolf, Evgenia Rusak, Steffen Schneider, Roland S. Zimmermann
Author-email: shifthappens@bethgelab.org
License: Apache 2.0
Project-URL: Bug Tracker, https://github.com/shift-happens-benchmark/2022
Classifier: Programming Language :: Python :: 3
Classifier: Intended Audience :: Developers
Classifier: License :: OSI Approved :: Apache Software License
Classifier: Topic :: Software Development :: Libraries
Classifier: Topic :: Utilities
Requires-Python: >=3.8
License-File: LICENSE
Provides-Extra: install_requires
Requires-Dist: pytest ; extra == 'install_requires'
Requires-Dist: numpy ; extra == 'install_requires'
